simplenote_cli/__init__.py
simplenote_cli/clipboard.py
simplenote_cli/config.py
simplenote_cli/notes_db.py
simplenote_cli/simplenote.py
simplenote_cli/sncli.py
simplenote_cli/temp.py
simplenote_cli/user_input.py
simplenote_cli/utils.py
simplenote_cli/view_help.py
simplenote_cli/view_log.py
simplenote_cli/view_note.py
simplenote_cli/view_titles.py
sncli-0.4.4.dist-info/licenses/LICENSE
sncli-0.4.4.dist-info/METADATA
sncli-0.4.4.dist-info/WHEEL
sncli-0.4.4.dist-info/entry_points.txt
sncli-0.4.4.dist-info/top_level.txt
sncli-0.4.4.dist-info/RECORD
