Metadata-Version: 2.4
Name: sncli
Version: 0.4.4
Summary: Simplenote Command Line Interface
Home-page: https://github.com/insanum/sncli
Author: Eric Davis
Author-email: edavis@insanum.com
License: MIT
Classifier: Development Status :: 5 - Production/Stable
Classifier: Environment :: Console :: Curses
Classifier: Intended Audience :: End Users/Desktop
Classifier: License :: OSI Approved :: MIT License
Classifier: Programming Language :: Python :: 3 :: Only
Requires: urwid
Requires: requests
Requires: Simperium3
License-File: LICENSE
Requires-Dist: urwid
Requires-Dist: requests
Requires-Dist: Simperium3
Dynamic: author
Dynamic: author-email
Dynamic: classifier
Dynamic: home-page
Dynamic: license
Dynamic: license-file
Dynamic: requires
Dynamic: requires-dist
Dynamic: summary
